CHANGELOG.txt
LICENCE.txt
MANIFEST.in
README.txt
setup.py
PyMolecules/DoubleCircularLinkedList.py
PyMolecules/DoubleLinkedList.py
PyMolecules/SingleCircularLinkedList.py
PyMolecules/SingleLinkedList.py
PyMolecules/__init__.py
PyMolecules.egg-info/PKG-INFO
PyMolecules.egg-info/SOURCES.txt
PyMolecules.egg-info/dependency_links.txt
PyMolecules.egg-info/top_level.txt