Metadata-Version: 2.1
Name: PyMolecules
Version: 3.0.0
Summary: A Python package for all types of linked lists and most useful methods
Home-page: UNKNOWN
Author: Yokesh Bollineni
Author-email: bollineniyokesh@gmail.com
License: MIT
Keywords: linked lists
Platform: UNKNOWN
License-File: LICENCE.txt
